{
  "test_id": "N4-15",
  "level": "N4",
  "version": "2.0.0",
  "total_questions": 82,
  "time_limit_minutes": 90,
  "questions": [
    {
      "section": "漢字読み",
      "question": "彼は背が高いです。\n\n「背」の読み方は？",
      "options": [
        "そ",
        "う",
        "はい",
        "せ"
      ],
      "answer": 3
    },
    {
      "section": "漢字読み",
      "question": "荷物を届けてください。\n\n「届」の読み方は？",
      "options": [
        "とど",
        "わた",
        "つた",
        "おく"
      ],
      "answer": 0
    },
    {
      "section": "漢字読み",
      "question": "彼女は優しい性格です。\n\n「優」の読み方は？",
      "options": [
        "ゆう",
        "まさ",
        "やさ",
        "すぐ"
      ],
      "answer": 2
    },
    {
      "section": "漢字読み",
      "question": "音楽を楽しみながら勉強します。\n\n「楽」の読み方は？",
      "options": [
        "たの",
        "たの",
        "がく",
        "らく"
      ],
      "answer": 0
    },
    {
      "section": "漢字読み",
      "question": "交通事故に注意してください。\n\n「注意」の読み方は？",
      "options": [
        "ちゅうい",
        "しゅい",
        "しゅうい",
        "ちゅい"
      ],
      "answer": 0
    },
    {
      "section": "漢字読み",
      "question": "この店は品質がいいです。\n\n「品質」の読み方は？",
      "options": [
        "ひんしつ",
        "ひんしち",
        "しなしち",
        "しなしつ"
      ],
      "answer": 0
    },
    {
      "section": "漢字読み",
      "question": "彼は約束を守る人です。\n\n「約束」の読み方は？",
      "options": [
        "やっそく",
        "やくそこ",
        "やくそっく",
        "やくそく"
      ],
      "answer": 3
    },
    {
      "section": "漢字読み",
      "question": "この問題は複雑です。\n\n「複雑」の読み方は？",
      "options": [
        "ふくさつ",
        "ふくぞう",
        "ふくざつ",
        "ふざつ"
      ],
      "answer": 2
    },
    {
      "section": "漢字読み",
      "question": "明日の予定を確認しました。\n\n「確認」の読み方は？",
      "options": [
        "かくじん",
        "かくにん",
        "がくにん",
        "たしにん"
      ],
      "answer": 1
    },
    {
      "section": "表記",
      "question": "（あんぜん）の漢字は？",
      "options": [
        "安全",
        "暗全",
        "案全",
        "按全"
      ],
      "answer": 0
    },
    {
      "section": "表記",
      "question": "（えいが）の漢字は？",
      "options": [
        "永画",
        "映画",
        "泳画",
        "栄画"
      ],
      "answer": 1
    },
    {
      "section": "表記",
      "question": "（えいきょう）の漢字は？",
      "options": [
        "営響",
        "影響",
        "映響",
        "栄響"
      ],
      "answer": 1
    },
    {
      "section": "表記",
      "question": "（いけん）の漢字は？",
      "options": [
        "意見",
        "委見",
        "医見",
        "異見"
      ],
      "answer": 0
    },
    {
      "section": "表記",
      "question": "（とくべつ）の漢字は？",
      "options": [
        "独別",
        "特別",
        "得別",
        "徳別"
      ],
      "answer": 1
    },
    {
      "section": "表記",
      "question": "（せいかつ）の漢字は？",
      "options": [
        "青活",
        "生活",
        "正活",
        "声活"
      ],
      "answer": 1
    },
    {
      "section": "文脈規定",
      "question": "彼女は（　　）に説明してくれた。",
      "options": [
        "乱暴",
        "適当",
        "雑",
        "丁寧"
      ],
      "answer": 3
    },
    {
      "section": "文脈規定",
      "question": "彼女は（　　）な性格で、すぐに怒る。",
      "options": [
        "短気",
        "楽観的",
        "気長",
        "のんき"
      ],
      "answer": 0
    },
    {
      "section": "文脈規定",
      "question": "この問題は（　　）すぎて、解けない。",
      "options": [
        "つまらな",
        "やさし",
        "難し",
        "おもしろ"
      ],
      "answer": 2
    },
    {
      "section": "文脈規定",
      "question": "この仕事は（　　）が必要です。",
      "options": [
        "運",
        "偶然",
        "失敗",
        "経験"
      ],
      "answer": 3
    },
    {
      "section": "文脈規定",
      "question": "試験に（　　）するために、毎日勉強している。",
      "options": [
        "合格",
        "棄権",
        "不合格",
        "失敗"
      ],
      "answer": 0
    },
    {
      "section": "文脈規定",
      "question": "この商品は（　　）がいいから、よく売れている。",
      "options": [
        "噂",
        "悪口",
        "批判",
        "評判"
      ],
      "answer": 3
    },
    {
      "section": "文脈規定",
      "question": "この計画を（　　）するには、時間がかかる。",
      "options": [
        "実行",
        "延期",
        "中止",
        "拒否"
      ],
      "answer": 0
    },
    {
      "section": "文脈規定",
      "question": "彼女の話は（　　）信じられない。",
      "options": [
        "ちょっと",
        "きっと",
        "たぶん",
        "とても"
      ],
      "answer": 3
    },
    {
      "section": "文脈規定",
      "question": "この店は（　　）がいいから、よく来る。",
      "options": [
        "キャンセル",
        "トラブル",
        "サービス",
        "クレーム"
      ],
      "answer": 2
    },
    {
      "section": "文脈規定",
      "question": "この本は（　　）がおもしろい。",
      "options": [
        "表紙",
        "外見",
        "紙質",
        "内容"
      ],
      "answer": 3
    },
    {
      "section": "言い換え類義",
      "question": "「たくさん」と同じ意味の言葉は？",
      "options": [
        "大勢",
        "少し",
        "誰も",
        "一人"
      ],
      "answer": 0
    },
    {
      "section": "言い換え類義",
      "question": "「速い」と同じ意味の言葉は？",
      "options": [
        "遅い",
        "ゆっくり",
        "迅速",
        "のろい"
      ],
      "answer": 2
    },
    {
      "section": "言い換え類義",
      "question": "「親切」と同じ意味の言葉は？",
      "options": [
        "冷たい",
        "やさしい",
        "怖い",
        "厳しい"
      ],
      "answer": 1
    },
    {
      "section": "言い換え類義",
      "question": "「便利」と同じ意味の言葉は？",
      "options": [
        "面倒",
        "不便",
        "役立つ",
        "厄介"
      ],
      "answer": 2
    },
    {
      "section": "言い換え類義",
      "question": "「大きい」と同じ意味の言葉は？",
      "options": [
        "狭い",
        "巨大",
        "小さい",
        "微小"
      ],
      "answer": 1
    },
    {
      "section": "用法",
      "question": "「届く」の使い方で正しいものは？",
      "options": [
        "荷物が届いたら、連絡してください。",
        "友達が届いたら、案内してください。",
        "バスが届いたら、降りてください。",
        "電車が届いたら、乗ってください。"
      ],
      "answer": 0
    },
    {
      "section": "用法",
      "question": "「目」の使い方で正しいものは？",
      "options": [
        "目を書く。",
        "目を着る。",
        "目が覚める。",
        "目を食べる。"
      ],
      "answer": 2
    },
    {
      "section": "用法",
      "question": "「口」の使い方で正しいものは？",
      "options": [
        "口を読む。",
        "口を走る。",
        "口に出す。",
        "口を泳ぐ。"
      ],
      "answer": 2
    },
    {
      "section": "用法",
      "question": "「気」の使い方で正しいものは？",
      "options": [
        "気を着る。",
        "気を食べる。",
        "気を読む。",
        "気が付く。"
      ],
      "answer": 3
    },
    {
      "section": "用法",
      "question": "「胸」の使い方で正しいものは？",
      "options": [
        "胸を聞く。",
        "胸が痛む。",
        "胸を読む。",
        "胸を着る。"
      ],
      "answer": 1
    },
    {
      "section": "文法形式判断",
      "question": "この本は難しくて読（　　）ない。",
      "options": [
        "み",
        "ま",
        "め",
        "わ"
      ],
      "answer": 2
    },
    {
      "section": "文法形式判断",
      "question": "この映画は面白い（　　）と思います。",
      "options": [
        "く",
        "だ",
        "",
        "に"
      ],
      "answer": 2
    },
    {
      "section": "文法形式判断",
      "question": "この本は誰（　　）読めます。",
      "options": [
        "にも",
        "か",
        "でも",
        "も"
      ],
      "answer": 2
    },
    {
      "section": "文法形式判断",
      "question": "この本は読む（　　）があります。",
      "options": [
        "価値",
        "理由",
        "意味",
        "値打ち"
      ],
      "answer": 0
    },
    {
      "section": "文法形式判断",
      "question": "会議は（　　）終わりました。",
      "options": [
        "やっと",
        "まだ",
        "もう",
        "すぐ"
      ],
      "answer": 0
    },
    {
      "section": "文法形式判断",
      "question": "この料理は母が作った（　　）おいしい。",
      "options": [
        "だけあって",
        "ことで",
        "ものに",
        "ばかりで"
      ],
      "answer": 0
    },
    {
      "section": "文法形式判断",
      "question": "彼（　　）聞いてみましょう。",
      "options": [
        "で",
        "が",
        "を",
        "に"
      ],
      "answer": 3
    },
    {
      "section": "文法形式判断",
      "question": "雨が降り（　　）なので、傘を持っていきます。",
      "options": [
        "そう",
        "らしい",
        "よう",
        "みたい"
      ],
      "answer": 0
    },
    {
      "section": "文法形式判断",
      "question": "宿題を（　　）から、遊びに行きます。",
      "options": [
        "してに",
        "してから",
        "してと",
        "しての"
      ],
      "answer": 1
    },
    {
      "section": "文法形式判断",
      "question": "どこ（　　）行きましょうか。",
      "options": [
        "を",
        "へ",
        "に",
        "で"
      ],
      "answer": 1
    },
    {
      "section": "文法形式判断",
      "question": "日本に来（　　）一年になる。",
      "options": [
        "るから",
        "たから",
        "てで",
        "てから"
      ],
      "answer": 3
    },
    {
      "section": "文法形式判断",
      "question": "明日（　　）行きます。",
      "options": [
        "きっと",
        "もしかしたら",
        "必ず",
        "たぶん"
      ],
      "answer": 2
    },
    {
      "section": "文法形式判断",
      "question": "日本語が話せる（　　）なりました。",
      "options": [
        "ことに",
        "ように",
        "ために",
        "ものに"
      ],
      "answer": 1
    },
    {
      "section": "文法形式判断",
      "question": "彼は何も言わ（　　）帰ってしまった。",
      "options": [
        "ないで",
        "ずに",
        "ないに",
        "なくて"
      ],
      "answer": 1
    },
    {
      "section": "文法形式判断",
      "question": "彼女はきれい（　　）賢い。",
      "options": [
        "く",
        "と",
        "に",
        "で"
      ],
      "answer": 3
    },
    {
      "section": "文の組み立て",
      "question": "次の言葉を正しい順番に並べてください。\n昨日 / 私は / 見ました / 映画を",
      "options": [
        "映画を私は昨日見ました",
        "昨日私は映画を見ました",
        "私は昨日映画を見ました",
        "見ました映画を私は昨日"
      ],
      "answer": 2
    },
    {
      "section": "文の組み立て",
      "question": "次の言葉を正しい順番に並べてください。\n見ました / 映画を / 昨日 / 私は",
      "options": [
        "私は昨日映画を見ました",
        "見ました映画を私は昨日",
        "映画を私は昨日見ました",
        "昨日私は映画を見ました"
      ],
      "answer": 0
    },
    {
      "section": "文の組み立て",
      "question": "次の言葉を正しい順番に並べてください。\n昨日 / 映画を / 私は / 見ました",
      "options": [
        "見ました映画を私は昨日",
        "映画を私は昨日見ました",
        "昨日私は映画を見ました",
        "私は昨日映画を見ました"
      ],
      "answer": 3
    },
    {
      "section": "文の組み立て",
      "question": "次の言葉を正しい順番に並べてください。\n見ました / 昨日 / 映画を / 私は",
      "options": [
        "見ました映画を私は昨日",
        "昨日私は映画を見ました",
        "私は昨日映画を見ました",
        "映画を私は昨日見ました"
      ],
      "answer": 2
    },
    {
      "section": "文の組み立て",
      "question": "次の言葉を正しい順番に並べてください。\n映画を / 見ました / 昨日 / 私は",
      "options": [
        "映画を私は昨日見ました",
        "見ました映画を私は昨日",
        "私は昨日映画を見ました",
        "昨日私は映画を見ました"
      ],
      "answer": 2
    },
    {
      "section": "文章の文法",
      "question": "次の文章の（　）に入る言葉は？\n\nこの映画は面白い（　　）と思います。",
      "options": [
        "だ",
        "に",
        "",
        "く"
      ],
      "answer": 2
    },
    {
      "section": "文章の文法",
      "question": "次の文章の（　）に入る言葉は？\n\nもっと分かりやす（　　）説明してください。",
      "options": [
        "いに",
        "く",
        "くて",
        "い"
      ],
      "answer": 1
    },
    {
      "section": "文章の文法",
      "question": "次の文章の（　）に入る言葉は？\n\n宿題を（　　）から、遊びに行きます。",
      "options": [
        "してに",
        "しての",
        "してから",
        "してと"
      ],
      "answer": 2
    },
    {
      "section": "文章の文法",
      "question": "次の文章の（　）に入る言葉は？\n\n部長に資料を（　　）。",
      "options": [
        "見せてあげました",
        "見せてさしあげました",
        "お見せになりました",
        "お見せしました"
      ],
      "answer": 3
    },
    {
      "section": "文章の文法",
      "question": "次の文章の（　）に入る言葉は？\n\n明日までに終わらせ（　　）ください。",
      "options": [
        "って",
        "る",
        "て",
        "り"
      ],
      "answer": 2
    },
    {
      "section": "内容理解（短文）",
      "question": "日本では、4月に新学期が始まります。多くの会社も4月に新入社員を迎えます。桜の季節と重なるので、入学式や入社式では桜を背景に写真を撮る人が多いです。\n\n日本で新学期が始まるのはいつですか。",
      "options": [
        "1月",
        "3月",
        "9月",
        "4月"
      ],
      "answer": 3
    },
    {
      "section": "内容理解（短文）",
      "question": "私は毎朝6時に起きます。起きてからすぐシャワーを浴びて、朝ごはんを食べます。7時半に家を出て、8時に会社に着きます。会社まで電車で30分かかります。\n\nこの人は何時に家を出ますか。",
      "options": [
        "8時",
        "7時半",
        "7時",
        "6時"
      ],
      "answer": 1
    },
    {
      "section": "内容理解（短文）",
      "question": "最近、スマートフォンを使う時間が増えています。特に若い人は、1日に5時間以上使う人もいます。目が疲れたり、睡眠不足になったりする人が増えているそうです。\n\nスマートフォンの使いすぎで何が起きていますか。",
      "options": [
        "目が疲れたり睡眠不足になる",
        "お金が足りなくなる",
        "友達が減る",
        "勉強ができなくなる"
      ],
      "answer": 0
    },
    {
      "section": "内容理解（短文）",
      "question": "明日の会議は、予定を変更して午後3時から始めます。場所は5階の会議室Aです。資料は各自で印刷して持ってきてください。\n\n会議は何時に始まりますか。",
      "options": [
        "午後3時",
        "午後5時",
        "午後1時",
        "午前10時"
      ],
      "answer": 0
    },
    {
      "section": "内容理解（中文）",
      "question": "日本の電車は時間に正確なことで有名です。1分でも遅れると、駅員がお詫びのアナウンスをします。海外から来た人は、この正確さに驚くことが多いです。\nしかし、この正確さを維持するためには、多くの人の努力が必要です。運転士、車掌、駅員など、たくさんの人が毎日一生懸命働いています。\nまた、乗客のマナーも大切です。電車の中では静かにする、列を作って並ぶなど、日本独特のルールがあります。\n\n電車が遅れると、駅員は何をしますか。",
      "options": [
        "何もしない",
        "乗客に謝る",
        "お詫びのアナウンスをする",
        "運転士を呼ぶ"
      ],
      "answer": 2
    },
    {
      "section": "内容理解（中文）",
      "question": "私は先週、初めて富士山に登りました。朝5時に出発して、午後3時にやっと頂上に着きました。途中で何度も休憩しましたが、とても疲れました。\nでも、頂上からの景色は本当にきれいで、苦労した甲斐がありました。雲の上から見る太陽は、今まで見たことのない美しさでした。\n下山は思ったより大変で、足が痛くなりました。次の日は筋肉痛で動けませんでしたが、いい経験になりました。また登りたいと思います。\n\nこの人は頂上からの景色をどう思いましたか。",
      "options": [
        "とてもきれいだった",
        "普通だった",
        "見えなかった",
        "あまりきれいではなかった"
      ],
      "answer": 0
    },
    {
      "section": "情報検索",
      "question": "【日本語教室のお知らせ】\n■クラス\n　初級クラス：月・水曜日 10:00〜12:00\n　中級クラス：火・木曜日 14:00〜16:00\n　上級クラス：金曜日 18:00〜20:00\n■料金：1か月 12,000円\n■場所：市民センター 3階\n■申し込み：電話または メールで\n\n料金はいくらですか。",
      "options": [
        "14,000円",
        "10,000円",
        "12,000円",
        "16,000円"
      ],
      "answer": 2
    },
    {
      "section": "情報検索",
      "question": "【市民プール案内】\n■時間：9:00〜21:00（日曜は18:00まで）\n■料金：大人500円、子供（小学生以下）300円、65歳以上300円\n■休み：毎月第3火曜日\n■注意：水泳帽を必ず着用してください。\n\n日曜日は何時まで開いていますか。",
      "options": [
        "18:00まで",
        "17:00まで",
        "20:00まで",
        "21:00まで"
      ],
      "answer": 0
    },
    {
      "section": "課題理解",
      "question": "【音声】\n電話で男の人と女の人が話しています。\n\n男：もしもし、山田です。今日の約束ですが、急に仕事が入って...\n女：そうですか。じゃ、明日はどうですか。\n男：明日なら大丈夫です。\n女：じゃ、明日、同じ時間にね。\n\n二人はいつ会いますか。",
      "options": [
        "今日",
        "来週",
        "明日",
        "会わない"
      ],
      "answer": 2
    },
    {
      "section": "課題理解",
      "question": "【音声】\n店で客と店員が話しています。\n\n客：すみません、このシャツ、Mサイズはありますか。\n店員：申し訳ございません。Mサイズは売り切れです。SサイズとLサイズならございますが。\n客：じゃ、Lサイズをください。\n\n客は何サイズのシャツを買いますか。",
      "options": [
        "Mサイズ",
        "Lサイズ",
        "買わない",
        "Sサイズ"
      ],
      "answer": 1
    },
    {
      "section": "課題理解",
      "question": "【音声】\n会社で男の人と女の人が話しています。\n\n男：すみません、この資料、明日の会議で使いたいんですが。\n女：はい、何部必要ですか。\n男：10部お願いします。\n女：わかりました。コピーしておきますね。\n\n女の人はこれから何をしますか。",
      "options": [
        "会議に出る",
        "男の人を手伝う",
        "資料を作る",
        "資料をコピーする"
      ],
      "answer": 3
    },
    {
      "section": "ポイント理解",
      "question": "【音声】\n男：週末はどこか行った？\n女：うん、友達と映画を見に行ったよ。その後、一緒にご飯を食べた。\n男：いいね。何の映画を見たの？\n\n女の人は週末何をしましたか。",
      "options": [
        "映画を見てご飯を食べた",
        "仕事をした",
        "買い物をした",
        "家で寝ていた"
      ],
      "answer": 0
    },
    {
      "section": "ポイント理解",
      "question": "【音声】\n女：どうしたの？元気がないね。\n男：最近、仕事が忙しくて、睡眠時間が足りないんだ。\n女：それは大変ね。週末はゆっくり休んだほうがいいよ。\n\n男の人は何に困っていますか。",
      "options": [
        "お金がないこと",
        "睡眠時間が足りないこと",
        "仕事がないこと",
        "友達がいないこと"
      ],
      "answer": 1
    },
    {
      "section": "発話表現",
      "question": "【状況】\n友達の家に行きました。玄関でお母さんに会いました。\n\n何と言いますか。",
      "options": [
        "ただいま",
        "いらっしゃいませ",
        "行ってきます",
        "おじゃまします"
      ],
      "answer": 3
    },
    {
      "section": "発話表現",
      "question": "【状況】\n電車でお年寄りに席を譲りたいです。\n\n何と言いますか。",
      "options": [
        "座れ",
        "座りなさい",
        "どうぞ、お座りください",
        "座ってください"
      ],
      "answer": 2
    },
    {
      "section": "発話表現",
      "question": "【状況】\n友達が荷物をたくさん持っています。手伝いたいです。\n\n何と言いますか。",
      "options": [
        "手伝え",
        "お手伝いしましょうか",
        "手伝ってください",
        "手伝います"
      ],
      "answer": 1
    },
    {
      "section": "即時応答",
      "question": "【音声】\nこの席、空いていますか。\n\n何と答えますか。",
      "options": [
        "はい、座っています",
        "いいえ、空いています",
        "はい、どうぞ"
      ],
      "answer": 2
    },
    {
      "section": "即時応答",
      "question": "【音声】\n今日はいい天気ですね。\n\n何と答えますか。",
      "options": [
        "そうですね",
        "はい、寒いです",
        "いいえ、雨です"
      ],
      "answer": 0
    },
    {
      "section": "即時応答",
      "question": "【音声】\nすみません、道を教えてください。\n\n何と答えますか。",
      "options": [
        "まっすぐ行ってください",
        "道を聞いてください",
        "すみません"
      ],
      "answer": 0
    },
    {
      "section": "即時応答",
      "question": "【音声】\nありがとうございます。\n\n何と答えますか。",
      "options": [
        "ありがとう",
        "どういたしまして",
        "すみません"
      ],
      "answer": 1
    },
    {
      "section": "即時応答",
      "question": "【音声】\n週末は何をしましたか。\n\n何と答えますか。",
      "options": [
        "映画を見ています",
        "映画を見ます",
        "映画を見ました"
      ],
      "answer": 2
    },
    {
      "section": "即時応答",
      "question": "【音声】\nお元気ですか。\n\n何と答えますか。",
      "options": [
        "いいえ、元気です",
        "はい、元気じゃないです",
        "はい、おかげさまで"
      ],
      "answer": 2
    }
  ]
}