{
  "test_id": "N4-18",
  "level": "N4",
  "version": "2.0.0",
  "total_questions": 82,
  "time_limit_minutes": 90,
  "questions": [
    {
      "section": "漢字読み",
      "question": "この本は厚いです。\n\n「厚」の読み方は？",
      "options": [
        "おお",
        "ふと",
        "あつ",
        "こう"
      ],
      "answer": 2
    },
    {
      "section": "漢字読み",
      "question": "彼女は留学生です。\n\n「留学」の読み方は？",
      "options": [
        "るうがく",
        "りゅうがく",
        "るがく",
        "りゅがく"
      ],
      "answer": 1
    },
    {
      "section": "漢字読み",
      "question": "山を登るのは大変です。\n\n「登」の読み方は？",
      "options": [
        "と",
        "とう",
        "あが",
        "のぼ"
      ],
      "answer": 3
    },
    {
      "section": "漢字読み",
      "question": "新しい仕事に慣れるまで大変でした。\n\n「慣」の読み方は？",
      "options": [
        "た",
        "か",
        "な",
        "つ"
      ],
      "answer": 2
    },
    {
      "section": "漢字読み",
      "question": "交通事故に注意してください。\n\n「注意」の読み方は？",
      "options": [
        "ちゅい",
        "ちゅうい",
        "しゅい",
        "しゅうい"
      ],
      "answer": 1
    },
    {
      "section": "漢字読み",
      "question": "彼女は髪が長いです。\n\n「髪」の読み方は？",
      "options": [
        "はつ",
        "かみ",
        "もう",
        "け"
      ],
      "answer": 1
    },
    {
      "section": "漢字読み",
      "question": "この問題を解くのに時間がかかった。\n\n「解」の読み方は？",
      "options": [
        "さ",
        "ほど",
        "か",
        "と"
      ],
      "answer": 3
    },
    {
      "section": "漢字読み",
      "question": "会議の準備をしています。\n\n「準備」の読み方は？",
      "options": [
        "じゅんぴ",
        "しゅんび",
        "じゅんび",
        "しゅんぴ"
      ],
      "answer": 2
    },
    {
      "section": "漢字読み",
      "question": "試験に合格しました。\n\n「合格」の読み方は？",
      "options": [
        "がっかく",
        "ごうがく",
        "がっかく",
        "ごうかく"
      ],
      "answer": 3
    },
    {
      "section": "表記",
      "question": "（かんたん）の漢字は？",
      "options": [
        "乾担",
        "完端",
        "簡単",
        "感嘆"
      ],
      "answer": 2
    },
    {
      "section": "表記",
      "question": "（あめ）の漢字は？",
      "options": [
        "雪",
        "雷",
        "風",
        "雨"
      ],
      "answer": 3
    },
    {
      "section": "表記",
      "question": "（えき）の漢字は？",
      "options": [
        "転",
        "駅",
        "駐",
        "軽"
      ],
      "answer": 1
    },
    {
      "section": "表記",
      "question": "（えいが）の漢字は？",
      "options": [
        "泳画",
        "栄画",
        "映画",
        "永画"
      ],
      "answer": 2
    },
    {
      "section": "表記",
      "question": "（しんせつ）の漢字は？",
      "options": [
        "真説",
        "心説",
        "親切",
        "新設"
      ],
      "answer": 2
    },
    {
      "section": "表記",
      "question": "（いけん）の漢字は？",
      "options": [
        "異見",
        "委見",
        "医見",
        "意見"
      ],
      "answer": 3
    },
    {
      "section": "文脈規定",
      "question": "彼は（　　）に仕事を終わらせた。",
      "options": [
        "だらだら",
        "めちゃくちゃ",
        "きちんと",
        "ばらばら"
      ],
      "answer": 2
    },
    {
      "section": "文脈規定",
      "question": "彼女の話は（　　）信じられない。",
      "options": [
        "きっと",
        "ちょっと",
        "たぶん",
        "とても"
      ],
      "answer": 3
    },
    {
      "section": "文脈規定",
      "question": "この店は（　　）がいい。",
      "options": [
        "放置",
        "無視",
        "拒絶",
        "接客"
      ],
      "answer": 3
    },
    {
      "section": "文脈規定",
      "question": "彼女は（　　）な性格で、すぐに怒る。",
      "options": [
        "短気",
        "楽観的",
        "のんき",
        "気長"
      ],
      "answer": 0
    },
    {
      "section": "文脈規定",
      "question": "彼は（　　）を持って仕事をしている。",
      "options": [
        "軽率",
        "適当",
        "無責任",
        "責任"
      ],
      "answer": 3
    },
    {
      "section": "文脈規定",
      "question": "彼は毎日（　　）して、日本語が上手になった。",
      "options": [
        "運動",
        "準備",
        "練習",
        "休憩"
      ],
      "answer": 2
    },
    {
      "section": "文脈規定",
      "question": "この計画を（　　）するには、時間がかかる。",
      "options": [
        "拒否",
        "中止",
        "実行",
        "延期"
      ],
      "answer": 2
    },
    {
      "section": "文脈規定",
      "question": "この店は（　　）がいいから、よく来る。",
      "options": [
        "サービス",
        "キャンセル",
        "クレーム",
        "トラブル"
      ],
      "answer": 0
    },
    {
      "section": "文脈規定",
      "question": "彼は（　　）に遅刻する。",
      "options": [
        "全く",
        "よく",
        "めったに",
        "たまに"
      ],
      "answer": 1
    },
    {
      "section": "文脈規定",
      "question": "彼女は（　　）に答えてくれた。",
      "options": [
        "皮肉",
        "正直",
        "嘘",
        "冗談"
      ],
      "answer": 1
    },
    {
      "section": "言い換え類義",
      "question": "「高い」と同じ意味の言葉は？",
      "options": [
        "格安",
        "高価",
        "無料",
        "安い"
      ],
      "answer": 1
    },
    {
      "section": "言い換え類義",
      "question": "「親切」と同じ意味の言葉は？",
      "options": [
        "やさしい",
        "怖い",
        "厳しい",
        "冷たい"
      ],
      "answer": 0
    },
    {
      "section": "言い換え類義",
      "question": "「危ない」と同じ意味の言葉は？",
      "options": [
        "穏やか",
        "平和",
        "安全",
        "危険"
      ],
      "answer": 3
    },
    {
      "section": "言い換え類義",
      "question": "「すぐに」と同じ意味の言葉は？",
      "options": [
        "たぶん",
        "決して",
        "まもなく",
        "ゆっくり"
      ],
      "answer": 2
    },
    {
      "section": "言い換え類義",
      "question": "「簡単」と同じ意味の言葉は？",
      "options": [
        "面倒",
        "やさしい",
        "複雑",
        "難しい"
      ],
      "answer": 1
    },
    {
      "section": "用法",
      "question": "「間に合う」の使い方で正しいものは？",
      "options": [
        "買い物に間に合いました。",
        "電車に間に合いました。",
        "勉強に間に合いました。",
        "仕事に間に合いました。"
      ],
      "answer": 1
    },
    {
      "section": "用法",
      "question": "「胸」の使い方で正しいものは？",
      "options": [
        "胸を聞く。",
        "胸を読む。",
        "胸を着る。",
        "胸が痛む。"
      ],
      "answer": 3
    },
    {
      "section": "用法",
      "question": "「気」の使い方で正しいものは？",
      "options": [
        "気を着る。",
        "気が付く。",
        "気を食べる。",
        "気を読む。"
      ],
      "answer": 1
    },
    {
      "section": "用法",
      "question": "「顔」の使い方で正しいものは？",
      "options": [
        "顔を聞く。",
        "顔が広い。",
        "顔を読む。",
        "顔を食べる。"
      ],
      "answer": 1
    },
    {
      "section": "用法",
      "question": "「目」の使い方で正しいものは？",
      "options": [
        "目が覚める。",
        "目を着る。",
        "目を書く。",
        "目を食べる。"
      ],
      "answer": 0
    },
    {
      "section": "文法形式判断",
      "question": "彼（　　）聞いてみましょう。",
      "options": [
        "を",
        "で",
        "に",
        "が"
      ],
      "answer": 2
    },
    {
      "section": "文法形式判断",
      "question": "この本は読む（　　）があります。",
      "options": [
        "理由",
        "値打ち",
        "価値",
        "意味"
      ],
      "answer": 2
    },
    {
      "section": "文法形式判断",
      "question": "彼は何も言わ（　　）帰ってしまった。",
      "options": [
        "ずに",
        "なくて",
        "ないに",
        "ないで"
      ],
      "answer": 0
    },
    {
      "section": "文法形式判断",
      "question": "この料理は母が作った（　　）おいしい。",
      "options": [
        "ものに",
        "ばかりで",
        "だけあって",
        "ことで"
      ],
      "answer": 2
    },
    {
      "section": "文法形式判断",
      "question": "明日（　　）行きます。",
      "options": [
        "もしかしたら",
        "きっと",
        "たぶん",
        "必ず"
      ],
      "answer": 3
    },
    {
      "section": "文法形式判断",
      "question": "この映画は面白い（　　）と思います。",
      "options": [
        "だ",
        "く",
        "に",
        ""
      ],
      "answer": 3
    },
    {
      "section": "文法形式判断",
      "question": "彼は病気（　　）仕事を休んだ。",
      "options": [
        "を",
        "に",
        "で",
        "が"
      ],
      "answer": 2
    },
    {
      "section": "文法形式判断",
      "question": "日本に来（　　）一年になる。",
      "options": [
        "てで",
        "てから",
        "るから",
        "たから"
      ],
      "answer": 1
    },
    {
      "section": "文法形式判断",
      "question": "どこ（　　）行きましょうか。",
      "options": [
        "で",
        "を",
        "に",
        "へ"
      ],
      "answer": 3
    },
    {
      "section": "文法形式判断",
      "question": "部長に資料を（　　）。",
      "options": [
        "見せてさしあげました",
        "お見せになりました",
        "見せてあげました",
        "お見せしました"
      ],
      "answer": 3
    },
    {
      "section": "文法形式判断",
      "question": "彼女は歌（　　）上手だ。",
      "options": [
        "を",
        "に",
        "で",
        "が"
      ],
      "answer": 3
    },
    {
      "section": "文法形式判断",
      "question": "この料理は辛（　　）ぎます。",
      "options": [
        "さ",
        "く",
        "し",
        "す"
      ],
      "answer": 3
    },
    {
      "section": "文法形式判断",
      "question": "日本語が話せる（　　）なりました。",
      "options": [
        "ように",
        "ことに",
        "ために",
        "ものに"
      ],
      "answer": 0
    },
    {
      "section": "文法形式判断",
      "question": "明日までに終わらせ（　　）ください。",
      "options": [
        "て",
        "り",
        "って",
        "る"
      ],
      "answer": 0
    },
    {
      "section": "文法形式判断",
      "question": "宿題を（　　）から、遊びに行きます。",
      "options": [
        "しての",
        "してから",
        "してと",
        "してに"
      ],
      "answer": 1
    },
    {
      "section": "文の組み立て",
      "question": "次の言葉を正しい順番に並べてください。\n私は / 見ました / 昨日 / 映画を",
      "options": [
        "私は昨日映画を見ました",
        "見ました映画を私は昨日",
        "昨日私は映画を見ました",
        "映画を私は昨日見ました"
      ],
      "answer": 0
    },
    {
      "section": "文の組み立て",
      "question": "次の言葉を正しい順番に並べてください。\n見ました / 映画を / 私は / 昨日",
      "options": [
        "見ました映画を私は昨日",
        "昨日私は映画を見ました",
        "映画を私は昨日見ました",
        "私は昨日映画を見ました"
      ],
      "answer": 3
    },
    {
      "section": "文の組み立て",
      "question": "次の言葉を正しい順番に並べてください。\n私は / 昨日 / 見ました / 映画を",
      "options": [
        "昨日私は映画を見ました",
        "映画を私は昨日見ました",
        "見ました映画を私は昨日",
        "私は昨日映画を見ました"
      ],
      "answer": 3
    },
    {
      "section": "文の組み立て",
      "question": "次の言葉を正しい順番に並べてください。\n昨日 / 映画を / 見ました / 私は",
      "options": [
        "私は昨日映画を見ました",
        "昨日私は映画を見ました",
        "見ました映画を私は昨日",
        "映画を私は昨日見ました"
      ],
      "answer": 0
    },
    {
      "section": "文の組み立て",
      "question": "次の言葉を正しい順番に並べてください。\n映画を / 見ました / 私は / 昨日",
      "options": [
        "見ました映画を私は昨日",
        "昨日私は映画を見ました",
        "私は昨日映画を見ました",
        "映画を私は昨日見ました"
      ],
      "answer": 2
    },
    {
      "section": "文章の文法",
      "question": "次の文章の（　）に入る言葉は？\n\nこの料理は辛（　　）ぎます。",
      "options": [
        "す",
        "さ",
        "く",
        "し"
      ],
      "answer": 0
    },
    {
      "section": "文章の文法",
      "question": "次の文章の（　）に入る言葉は？\n\n日本語が話せる（　　）なりました。",
      "options": [
        "ように",
        "ことに",
        "ために",
        "ものに"
      ],
      "answer": 0
    },
    {
      "section": "文章の文法",
      "question": "次の文章の（　）に入る言葉は？\n\nもっと分かりやす（　　）説明してください。",
      "options": [
        "くて",
        "いに",
        "く",
        "い"
      ],
      "answer": 2
    },
    {
      "section": "文章の文法",
      "question": "次の文章の（　）に入る言葉は？\n\nこの本は誰（　　）読めます。",
      "options": [
        "にも",
        "でも",
        "か",
        "も"
      ],
      "answer": 1
    },
    {
      "section": "文章の文法",
      "question": "次の文章の（　）に入る言葉は？\n\n雨が降りそう（　　）。",
      "options": [
        "だ",
        "です",
        "の",
        "な"
      ],
      "answer": 0
    },
    {
      "section": "内容理解（短文）",
      "question": "私は毎朝6時に起きます。起きてからすぐシャワーを浴びて、朝ごはんを食べます。7時半に家を出て、8時に会社に着きます。会社まで電車で30分かかります。\n\nこの人は何時に家を出ますか。",
      "options": [
        "7時半",
        "8時",
        "6時",
        "7時"
      ],
      "answer": 0
    },
    {
      "section": "内容理解（短文）",
      "question": "明日の会議は、予定を変更して午後3時から始めます。場所は5階の会議室Aです。資料は各自で印刷して持ってきてください。\n\n会議は何時に始まりますか。",
      "options": [
        "午後3時",
        "午後1時",
        "午後5時",
        "午前10時"
      ],
      "answer": 0
    },
    {
      "section": "内容理解（短文）",
      "question": "昨日、新しいレストランに行きました。料理はおいしかったですが、店員のサービスがあまりよくなかったです。値段は少し高かったですが、料理の味には満足しました。\n\nこの人はレストランで何に満足しましたか。",
      "options": [
        "店の雰囲気",
        "サービス",
        "値段",
        "料理の味"
      ],
      "answer": 3
    },
    {
      "section": "内容理解（短文）",
      "question": "私の趣味は読書です。特に小説が好きで、週に2冊ぐらい読みます。図書館で借りることが多いですが、好きな作家の本は買って集めています。\n\nこの人は好きな作家の本をどうしますか。",
      "options": [
        "買って集める",
        "図書館で借りる",
        "友達に借りる",
        "読まない"
      ],
      "answer": 0
    },
    {
      "section": "内容理解（中文）",
      "question": "私は先週、初めて富士山に登りました。朝5時に出発して、午後3時にやっと頂上に着きました。途中で何度も休憩しましたが、とても疲れました。\nでも、頂上からの景色は本当にきれいで、苦労した甲斐がありました。雲の上から見る太陽は、今まで見たことのない美しさでした。\n下山は思ったより大変で、足が痛くなりました。次の日は筋肉痛で動けませんでしたが、いい経験になりました。また登りたいと思います。\n\n下山後、この人はどうなりましたか。",
      "options": [
        "病院に行った",
        "筋肉痛で動けなかった",
        "また登った",
        "すぐ元気になった"
      ],
      "answer": 1
    },
    {
      "section": "内容理解（中文）",
      "question": "日本の電車は時間に正確なことで有名です。1分でも遅れると、駅員がお詫びのアナウンスをします。海外から来た人は、この正確さに驚くことが多いです。\nしかし、この正確さを維持するためには、多くの人の努力が必要です。運転士、車掌、駅員など、たくさんの人が毎日一生懸命働いています。\nまた、乗客のマナーも大切です。電車の中では静かにする、列を作って並ぶなど、日本独特のルールがあります。\n\n日本の電車内のマナーとして正しいものは何ですか。",
      "options": [
        "走り回る",
        "音楽を聴く",
        "静かにする",
        "大声で話す"
      ],
      "answer": 2
    },
    {
      "section": "情報検索",
      "question": "【市民プール案内】\n■時間：9:00〜21:00（日曜は18:00まで）\n■料金：大人500円、子供（小学生以下）300円、65歳以上300円\n■休み：毎月第3火曜日\n■注意：水泳帽を必ず着用してください。\n\n65歳以上の人の料金はいくらですか。",
      "options": [
        "無料",
        "400円",
        "500円",
        "300円"
      ],
      "answer": 3
    },
    {
      "section": "情報検索",
      "question": "【日本語教室のお知らせ】\n■クラス\n　初級クラス：月・水曜日 10:00〜12:00\n　中級クラス：火・木曜日 14:00〜16:00\n　上級クラス：金曜日 18:00〜20:00\n■料金：1か月 12,000円\n■場所：市民センター 3階\n■申し込み：電話または メールで\n\n料金はいくらですか。",
      "options": [
        "10,000円",
        "14,000円",
        "16,000円",
        "12,000円"
      ],
      "answer": 3
    },
    {
      "section": "課題理解",
      "question": "【音声】\n電話で男の人と女の人が話しています。\n\n男：もしもし、山田です。今日の約束ですが、急に仕事が入って...\n女：そうですか。じゃ、明日はどうですか。\n男：明日なら大丈夫です。\n女：じゃ、明日、同じ時間にね。\n\n二人はいつ会いますか。",
      "options": [
        "今日",
        "会わない",
        "来週",
        "明日"
      ],
      "answer": 3
    },
    {
      "section": "課題理解",
      "question": "【音声】\n会社で男の人と女の人が話しています。\n\n男：すみません、この資料、明日の会議で使いたいんですが。\n女：はい、何部必要ですか。\n男：10部お願いします。\n女：わかりました。コピーしておきますね。\n\n女の人はこれから何をしますか。",
      "options": [
        "会議に出る",
        "資料を作る",
        "資料をコピーする",
        "男の人を手伝う"
      ],
      "answer": 2
    },
    {
      "section": "課題理解",
      "question": "【音声】\n店で客と店員が話しています。\n\n客：すみません、このシャツ、Mサイズはありますか。\n店員：申し訳ございません。Mサイズは売り切れです。SサイズとLサイズならございますが。\n客：じゃ、Lサイズをください。\n\n客は何サイズのシャツを買いますか。",
      "options": [
        "Mサイズ",
        "買わない",
        "Sサイズ",
        "Lサイズ"
      ],
      "answer": 3
    },
    {
      "section": "ポイント理解",
      "question": "【音声】\n女：どうしたの？元気がないね。\n男：最近、仕事が忙しくて、睡眠時間が足りないんだ。\n女：それは大変ね。週末はゆっくり休んだほうがいいよ。\n\n男の人は何に困っていますか。",
      "options": [
        "睡眠時間が足りないこと",
        "お金がないこと",
        "仕事がないこと",
        "友達がいないこと"
      ],
      "answer": 0
    },
    {
      "section": "ポイント理解",
      "question": "【音声】\n男：週末はどこか行った？\n女：うん、友達と映画を見に行ったよ。その後、一緒にご飯を食べた。\n男：いいね。何の映画を見たの？\n\n女の人は週末何をしましたか。",
      "options": [
        "仕事をした",
        "買い物をした",
        "映画を見てご飯を食べた",
        "家で寝ていた"
      ],
      "answer": 2
    },
    {
      "section": "発話表現",
      "question": "【状況】\n友達が荷物をたくさん持っています。手伝いたいです。\n\n何と言いますか。",
      "options": [
        "お手伝いしましょうか",
        "手伝ってください",
        "手伝います",
        "手伝え"
      ],
      "answer": 0
    },
    {
      "section": "発話表現",
      "question": "【状況】\n電車でお年寄りに席を譲りたいです。\n\n何と言いますか。",
      "options": [
        "座りなさい",
        "座ってください",
        "どうぞ、お座りください",
        "座れ"
      ],
      "answer": 2
    },
    {
      "section": "発話表現",
      "question": "【状況】\n友達の家に行きました。玄関でお母さんに会いました。\n\n何と言いますか。",
      "options": [
        "おじゃまします",
        "ただいま",
        "行ってきます",
        "いらっしゃいませ"
      ],
      "answer": 0
    },
    {
      "section": "即時応答",
      "question": "【音声】\nお元気ですか。\n\n何と答えますか。",
      "options": [
        "いいえ、元気です",
        "はい、元気じゃないです",
        "はい、おかげさまで"
      ],
      "answer": 2
    },
    {
      "section": "即時応答",
      "question": "【音声】\nありがとうございます。\n\n何と答えますか。",
      "options": [
        "すみません",
        "どういたしまして",
        "ありがとう"
      ],
      "answer": 1
    },
    {
      "section": "即時応答",
      "question": "【音声】\nすみません、道を教えてください。\n\n何と答えますか。",
      "options": [
        "道を聞いてください",
        "まっすぐ行ってください",
        "すみません"
      ],
      "answer": 1
    },
    {
      "section": "即時応答",
      "question": "【音声】\n週末は何をしましたか。\n\n何と答えますか。",
      "options": [
        "映画を見ました",
        "映画を見ます",
        "映画を見ています"
      ],
      "answer": 0
    },
    {
      "section": "即時応答",
      "question": "【音声】\nこの席、空いていますか。\n\n何と答えますか。",
      "options": [
        "はい、どうぞ",
        "いいえ、空いています",
        "はい、座っています"
      ],
      "answer": 0
    },
    {
      "section": "即時応答",
      "question": "【音声】\n今日はいい天気ですね。\n\n何と答えますか。",
      "options": [
        "そうですね",
        "いいえ、雨です",
        "はい、寒いです"
      ],
      "answer": 0
    }
  ]
}